{
  "creds": {
    "noiseKey": {
      "private": {
        "type": "Buffer",
        "data": "OFrERye6FgAgcMpfZ0QShC+RGjn8EKQnGkJxyiLiYkI="
      },
      "public": {
        "type": "Buffer",
        "data": "Ak5r20zFBvPefc5hPQRppMU1Cm1r7cHmEW2MATwaAwA="
      }
    },
    "signedIdentityKey": {
      "private": {
        "type": "Buffer",
        "data": "QIWAS8tJS8K/P2FYqHBjLVfCQoZh+BM1wFmvhdUPOkg="
      },
      "public": {
        "type": "Buffer",
        "data": "fftpabCusAnoXfIAaBBKjnmL/tLVSz6N0ouP100Glmc="
      }
    },
    "signedPreKey": {
      "keyPair": {
        "private": {
          "type": "Buffer",
          "data": "oHvbcro9eCJ1KvJsFOgLzXs2k3J9dJSiR5ShTxRvQF0="
        },
        "public": {
          "type": "Buffer",
          "data": "AhaFVvWRPMbomflpnX4EBamOyNi/OkWtu7eAC4TpomA="
        }
      },
      "signature": {
        "type": "Buffer",
        "data": "WacpgpmOEC8kQcbtPdY4vCVm8Q1kjH1sq3Lea7J5TAYPymYQ7sinfdbiNlt0wQ6D1+p2tJq5iQjZLi3EASoUhQ=="
      },
      "keyId": 1
    },
    "registrationId": 221,
    "advSecretKey": "ghfRCZp2tMJR9o6fwH259h69L4Pp1zYqbDvWslVKZ38=",
    "processedHistoryMessages": [
      {
        "key": {
          "remoteJid": "50940209213@s.whatsapp.net",
          "fromMe": true,
          "id": "BB43640354FA97C92B0B522FFB9101F3"
        },
        "messageTimestamp": 1664711328
      },
      {
        "key": {
          "remoteJid": "50940209213@s.whatsapp.net",
          "fromMe": true,
          "id": "176AEEED2A954B8588ACEAB73637466E"
        },
        "messageTimestamp": 1664711329
      },
      {
        "key": {
          "remoteJid": "50940209213@s.whatsapp.net",
          "fromMe": true,
          "id": "CD6589549762865C2B3BCEAC8BB668B5"
        },
        "messageTimestamp": 1664711333
      }
    ],
    "nextPreKeyId": 31,
    "firstUnuploadedPreKeyId": 31,
    "accountSettings": {
      "unarchiveChats": false
    },
    "account": {
      "details": "CJSEuAkQm/XlmQYYAQ==",
      "accountSignatureKey": "YRJdojsW3tZe0zpbPsKprZa1XemQQ3qeAanpwUW4BiA=",
      "accountSignature": "4vU/3IvkwD9cckuZFXEn7PLNKJsRUvwkK5Ji6wLkDjmJI4Us5JmKgJVEf38xBHrWqn3Wx2tYtUaETk+IQK6OAQ==",
      "deviceSignature": "NV2oj+2AayI7xopKxg/Wau9zIIBl/SOE7sje721JnB9cNAnZQr0FDKkfMrunrnljD8FlsULELNqmDXiwaULPjQ=="
    },
    "me": {
      "id": "50940209213:1@s.whatsapp.net",
      "name": "I'm lesti"
    },
    "signalIdentities": [
      {
        "identifier": {
          "name": "50940209213:1@s.whatsapp.net",
          "deviceId": 0
        },
        "identifierKey": {
          "type": "Buffer",
          "data": "BWESXaI7Ft7WXtM6Wz7Cqa2WtV3pkEN6ngGp6cFFuAYg"
        }
      }
    ],
    "platform": "android",
    "lastAccountSyncTimestamp": 1664711327,
    "myAppStateKeyId": "AAAAAL/p"
  },
  "keys": {
    "preKeys": {
      "1": {
        "private": {
          "type": "Buffer",
          "data": "MFi3vcPY/UbSyGFUmmu455ZDZ9uk9L6wqWx4ydetp14="
        },
        "public": {
          "type": "Buffer",
          "data": "LuhNn6j+35XItBsUjkM61JKSVw8HVukmqyFG9kuGp1o="
        }
      },
      "2": {
        "private": {
          "type": "Buffer",
          "data": "gFNXnT1rSf1Y48op0nTx0QWN82L0dYUEmp2XOACjH2E="
        },
        "public": {
          "type": "Buffer",
          "data": "kfjlNt0nZ3MSksz3Nw1TkuIq5odJwfeu0aYqU8DuuGs="
        }
      },
      "3": {
        "private": {
          "type": "Buffer",
          "data": "8KHAofF3yiZqw/Y79gpZqqW/xM8E+mbFiga5Sd3h0Uo="
        },
        "public": {
          "type": "Buffer",
          "data": "03iFfbQhVXRyV70LFjHKKXR/OBdrgsu3XcNhKwdTjXU="
        }
      },
      "4": {
        "private": {
          "type": "Buffer",
          "data": "SOeEtbRHsxf2YDymWH8AwIU6VLNjCD4L+0JGpGOyIWA="
        },
        "public": {
          "type": "Buffer",
          "data": "VNvl/nWi6xnHGa/V5sM1nH5QQ+9g4uTrsxxfPTi/Rms="
        }
      },
      "5": null,
      "6": {
        "private": {
          "type": "Buffer",
          "data": "ANFgUCu0bDFONs+I0lSl7Ns85YBusYNFKOBIg3+hsGg="
        },
        "public": {
          "type": "Buffer",
          "data": "A4W1YRXXMHWUf9/qSNSo2xiPG3t6uBPSRfEkvDk/6AQ="
        }
      },
      "7": {
        "private": {
          "type": "Buffer",
          "data": "CBfSctkNGrZ2YIIrxG/7cXnCG9FORW757vsBWGwkKXE="
        },
        "public": {
          "type": "Buffer",
          "data": "17eEa/xBsggZgR4PYzcnCZdkNiRezICVlCIAEi7HI0I="
        }
      },
      "8": {
        "private": {
          "type": "Buffer",
          "data": "aGre0lzc9ZoDotqzpekC5d7QqMP3bUTozPYiEirCXV8="
        },
        "public": {
          "type": "Buffer",
          "data": "aHJ1EMbeo7hC7Q2O8aqOSpKfFKeAcjBQaBlNqN+W3S8="
        }
      },
      "9": {
        "private": {
          "type": "Buffer",
          "data": "6L8d6KPJR/kmCKxWYMF3WT58GX+tIOZXvMeN2oB6rVc="
        },
        "public": {
          "type": "Buffer",
          "data": "JMn0gNajtfSVaHqIEuOL2vVEFJAL12rSr/KcAPtM9UQ="
        }
      },
      "10": {
        "private": {
          "type": "Buffer",
          "data": "WFzgvdiF4feOkKdEtJJj8YFFB3NsFWGU7Pz79ZUr7EU="
        },
        "public": {
          "type": "Buffer",
          "data": "eDlY476IT1pDfG0tNoUfmvhyWpp4iyCNTrGXy/6FVzc="
        }
      },
      "11": {
        "private": {
          "type": "Buffer",
          "data": "EIC6POpftpqI7jKhI8yJosjasxY8+9AxF6MbdARc5lw="
        },
        "public": {
          "type": "Buffer",
          "data": "A+XE1HZ6DgGDax+R7EhuciCbtOkOhXCU6oXpH1xAXyI="
        }
      },
      "12": {
        "private": {
          "type": "Buffer",
          "data": "6IhRj/62UvdwJ6TBTsGS2Ru1ejMxfDprHmyhYF17aUo="
        },
        "public": {
          "type": "Buffer",
          "data": "PqxQVeg1LerZjrz8wm9q36FwkFx2t4i0omsWzaSLMGw="
        }
      },
      "13": {
        "private": {
          "type": "Buffer",
          "data": "+CKCe/sUe9M5pTX9ZndS41iw5oKYJm+dqJSD2osUNk4="
        },
        "public": {
          "type": "Buffer",
          "data": "gWSpLr1oZp2qAVc0i4VlhY2QOSRXqZb1HgA0Pcb/yW0="
        }
      },
      "14": {
        "private": {
          "type": "Buffer",
          "data": "kFj4v1waohNKWYZfEYGpohkcb8nI69VMP4a7uuzQX24="
        },
        "public": {
          "type": "Buffer",
          "data": "u5ssSfVIkVrfnPvaMsPNclRRd93i6Fqw5z4OUm+p9BM="
        }
      },
      "15": {
        "private": {
          "type": "Buffer",
          "data": "mDuk83Th5VK1YMGBQ23JWkksrZQ8ez5XpHUw/5/Xp2I="
        },
        "public": {
          "type": "Buffer",
          "data": "qCvWOMgMTVik4Q41NT/qZZVJKHzo2dA4xX+s7aRQ2jE="
        }
      },
      "16": {
        "private": {
          "type": "Buffer",
          "data": "eDC9f2xMr3c37yt3MxsJkRatCLQpMvyqNNMl4W0jlko="
        },
        "public": {
          "type": "Buffer",
          "data": "KgA681qgD7qQf+IdT6lvNQ8J1EBgM9/ezhK3kLXTglc="
        }
      },
      "17": {
        "private": {
          "type": "Buffer",
          "data": "QPxSYTgEkek83jUbgMTSg1HAOzMBsrLwsxNhjZdFAkU="
        },
        "public": {
          "type": "Buffer",
          "data": "WFOwPj0K9nf+YUplgQMATLsubvUhruHQNR1mrbDZuSE="
        }
      },
      "18": {
        "private": {
          "type": "Buffer",
          "data": "QD4jFkfAhEwBtnz85TWbvuvloBm7yCWvmI5Pf4tREGY="
        },
        "public": {
          "type": "Buffer",
          "data": "fIKoZr+5yCvJ5HRYf5db2VZlqzPaNLyV+m4P7A0D5CM="
        }
      },
      "19": {
        "private": {
          "type": "Buffer",
          "data": "OD9SU23KY2Z7qsoonGW16uvYdE1M6i389Q8yvhdse3k="
        },
        "public": {
          "type": "Buffer",
          "data": "FQV8N+2ZuB6+gbEG5mqeENKL4SiL4i4m+KTNA5rTgGg="
        }
      },
      "20": {
        "private": {
          "type": "Buffer",
          "data": "iKHBDuVPDCQjXmRSQoY/Q8Qh2rhBsufiT80S09fyjmo="
        },
        "public": {
          "type": "Buffer",
          "data": "N8mqrS4swKfpecuPOwXwcNpqsTKZAgIyOLQ0ZEZ3Fn8="
        }
      },
      "21": {
        "private": {
          "type": "Buffer",
          "data": "mB7ALTmIx+zs78iLFjMx7ofgs1hiRgbdVvxZ36gSHGw="
        },
        "public": {
          "type": "Buffer",
          "data": "y9QPeVLp3gN2X1k552jBi/vWFObuBWyGgh+9P8/a20M="
        }
      },
      "22": {
        "private": {
          "type": "Buffer",
          "data": "uL0o3N3fHzyIdFWHFJWA4X7/W8Ubyig6QDKu2nK0ZGA="
        },
        "public": {
          "type": "Buffer",
          "data": "LUwbQFyqDWMnqdwSWO4UzB/D14vE9bmRFecqdpQFOAI="
        }
      },
      "23": {
        "private": {
          "type": "Buffer",
          "data": "CJLor3t5UWxSIp5Twhh8mIV7g665R2lem12tduTxe0c="
        },
        "public": {
          "type": "Buffer",
          "data": "svulWpnErz6Bao4rDQtdoGI846HCTe5bsGf0jklVpSY="
        }
      },
      "24": {
        "private": {
          "type": "Buffer",
          "data": "aE2KIXOwA/MGhWUiZLJIy0b7Zi1sYnSIrZe8JaeFO24="
        },
        "public": {
          "type": "Buffer",
          "data": "DWOeBdOxe5h2p2C0mayiJsyB42re6QScOUPSmK5XcG4="
        }
      },
      "25": {
        "private": {
          "type": "Buffer",
          "data": "KKmCJgST3XMK0vcBHZM/fzjaiWa9QA0pzomsaK5DElk="
        },
        "public": {
          "type": "Buffer",
          "data": "INy3eVkwFAX0lFEiB2Iet3bHglbg5wsVh5iNd5rhPwo="
        }
      },
      "26": {
        "private": {
          "type": "Buffer",
          "data": "UG1SRUitlMzh3KiDHC78XbvIdh5irTFWldQRgYD70nc="
        },
        "public": {
          "type": "Buffer",
          "data": "RqgoUl4hnL2XWiOGGdIYQtWGoWZEtV9d5DiEia5EUjE="
        }
      },
      "27": {
        "private": {
          "type": "Buffer",
          "data": "GGP/Fjb4j+TLy9cLtZNlWAROUctI5uAS4QPPn2iGQW8="
        },
        "public": {
          "type": "Buffer",
          "data": "SQPjNkfQsJQOEvGpr8t9/csAs/8tvh5SpkgVwoRoxWA="
        }
      },
      "28": {
        "private": {
          "type": "Buffer",
          "data": "KELq4e0GyIk+Pgk+dMJ0LQ2QK0gBS31mBqHLjYYgMFE="
        },
        "public": {
          "type": "Buffer",
          "data": "DUBM0FIWudQdgu2OV3DCnN1yVTP5V33XkvJtjRgiY3A="
        }
      },
      "29": null,
      "30": {
        "private": {
          "type": "Buffer",
          "data": "QNLLrFROFUazaksf1eUeSA8WcLJ/oOtdey7r9Vt5RGQ="
        },
        "public": {
          "type": "Buffer",
          "data": "ECkLfaa2xOE1sZs/+MkaDIxa/UTMpkD7Vj1dwghQJwA="
        }
      }
    },
    "sessions": {
      "50940209213.0": {
        "_sessions": {
          "BZeMKOrBgx+Um6w8kwSEqSjJvDmBoGT2alqtLWTMrD1U": {
            "registrationId": 1720049337,
            "currentRatchet": {
              "ephemeralKeyPair": {
                "pubKey": "BVcQ7fclRrwbKtGJSsdKCO5lJGRf/KheqMc//m7l9bMf",
                "privKey": "UG2qiYnHULNzXOqvtf8KkFk+5GrV2efdztS4/6mvWkw="
              },
              "lastRemoteEphemeralKey": "BRMXah6UTAmW3wxafVS8amEWOB9QFGRS7rzFwOs4H/UR",
              "previousCounter": 0,
              "rootKey": "TU+gXyAoZzAD+PqPwVsixu0vBO0CWrDrJA8sR4GB2uI="
            },
            "indexInfo": {
              "baseKey": "BZeMKOrBgx+Um6w8kwSEqSjJvDmBoGT2alqtLWTMrD1U",
              "baseKeyType": 2,
              "closed": -1,
              "used": 1664711328407,
              "created": 1664711328407,
              "remoteIdentityKey": "BWESXaI7Ft7WXtM6Wz7Cqa2WtV3pkEN6ngGp6cFFuAYg"
            },
            "_chains": {
              "BRMXah6UTAmW3wxafVS8amEWOB9QFGRS7rzFwOs4H/UR": {
                "chainKey": {
                  "counter": 6,
                  "key": "4aUevOFsr+WaHGmA2u8Ij7gsn7a0TFwafeWG34TNOIk="
                },
                "chainType": 2,
                "messageKeys": {}
              },
              "BVcQ7fclRrwbKtGJSsdKCO5lJGRf/KheqMc//m7l9bMf": {
                "chainKey": {
                  "counter": 1,
                  "key": "WTn+656Ynzz6keULYh1OV0pfr4ZcD1kk8JfR4WivqWQ="
                },
                "chainType": 1,
                "messageKeys": {}
              }
            }
          }
        },
        "version": "v1"
      },
      "6283866284190.0": {
        "_sessions": {
          "BQJU29Hy8cnCcemWmor2la0wVdFTYwv2YJb6MyDfbAZr": {
            "registrationId": 1666017336,
            "currentRatchet": {
              "ephemeralKeyPair": {
                "pubKey": "BaNkwAZyJGjpk62B2QzX/ann5WsOiQOia4a60kcrr4xP",
                "privKey": "YFCMZpstzf83ovfB9P3T01v0ahCYxFO25b0w5cnqNEQ="
              },
              "lastRemoteEphemeralKey": "Bdp3kQK/hVHaZpLUsMvEzxkncC3m+BNR6dMr6SmqoRNJ",
              "previousCounter": 0,
              "rootKey": "4YYqHs4qrytiL0QoRnbZdO8CSbeXy2kfa8Kma7wU2kQ="
            },
            "indexInfo": {
              "baseKey": "BQJU29Hy8cnCcemWmor2la0wVdFTYwv2YJb6MyDfbAZr",
              "baseKeyType": 2,
              "closed": -1,
              "used": 1664711435681,
              "created": 1664711435681,
              "remoteIdentityKey": "BU6Hm1eKVyIeX4BXj/M/Xx+DFp3V6xAeG7bAm4KSwZk1"
            },
            "_chains": {
              "Bdp3kQK/hVHaZpLUsMvEzxkncC3m+BNR6dMr6SmqoRNJ": {
                "chainKey": {
                  "counter": 0,
                  "key": "hGjNzqyKqyZLkB9IxJfDcRMFCc86xbxcwYPB3uu4pHM="
                },
                "chainType": 2,
                "messageKeys": {}
              },
              "BaNkwAZyJGjpk62B2QzX/ann5WsOiQOia4a60kcrr4xP": {
                "chainKey": {
                  "counter": 1,
                  "key": "Eik4eFaYnaa1gvg89xy6EMld18LTEo7N3pHqpqRVOfY="
                },
                "chainType": 1,
                "messageKeys": {}
              }
            }
          }
        },
        "version": "v1"
      },
      "50946058112.0": {
        "_sessions": {
          "BT6l1oaWboneKudfW++EO7ntrd0cJbteMOSuBrxW1G8E": {
            "registrationId": 398193115,
            "currentRatchet": {
              "ephemeralKeyPair": {
                "pubKey": "BQ/3oTg/lJ7SLr0k1aTsGHaQr475Sve54TfhlH2YZB5/",
                "privKey": "WClT/jQq0H0/TqROI//UTQafJE+j4QTeFToVYO8C3H0="
              },
              "lastRemoteEphemeralKey": "BR4WucFeiOVdNQ1XIS0/viwk8KbyTzDPGrPlInm53ug6",
              "previousCounter": 0,
              "rootKey": "K+cgrZMGrTAtmcS/ksVm+Z3fVB+aPRQLrPV2QkXGfN0="
            },
            "indexInfo": {
              "baseKey": "BT6l1oaWboneKudfW++EO7ntrd0cJbteMOSuBrxW1G8E",
              "baseKeyType": 2,
              "closed": -1,
              "used": 1664711599799,
              "created": 1664711599799,
              "remoteIdentityKey": "BaxtdmKRKcgk2LwQIVt0Lum/8cm9goX0VwGNxKmAtkRI"
            },
            "_chains": {
              "BR4WucFeiOVdNQ1XIS0/viwk8KbyTzDPGrPlInm53ug6": {
                "chainKey": {
                  "counter": 0,
                  "key": "U9i3Wfzre9+ThqVW9Xa4N7bH6itAY7RENf3Ddq0Pk2M="
                },
                "chainType": 2,
                "messageKeys": {}
              },
              "BQ/3oTg/lJ7SLr0k1aTsGHaQr475Sve54TfhlH2YZB5/": {
                "chainKey": {
                  "counter": -1,
                  "key": "gAVjF8n3pvztK0pZdAPcfNUbblszPNzhMGdhTNdivdQ="
                },
                "chainType": 1,
                "messageKeys": {}
              }
            }
          }
        },
        "version": "v1"
      }
    },
    "appStateSyncKeys": {
      "AAAAAL/p": {
        "keyData": "I5TrUCNMq4+erm5MWLG8Cp6AClYarkLTFq9QM22/Ges=",
        "fingerprint": {
          "rawId": 19792404,
          "currentIndex": 1,
          "deviceIndexes": [
            0,
            1
          ]
        },
        "timestamp": "1664711328562"
      }
    },
    "appStateVersions": {
      "critical_block": {
        "version": 1,
        "hash": {
          "type": "Buffer",
          "data": "ffoeRrM024ADoFcZSp285bK9EthDjHi+3UxyW1iRHhQbLXcylDNYwfEs2IFuFWHlmpWkZlFZhQ88eIs1H8Dta1q0uteG+KwN4ZWk73HYCE+UPBRviofeCuFPUb8G4GGkUiUL3wTilrXpxFKFVjAo9F1XvbT8f9VYQKnJMMKwaqs="
        },
        "indexValueMap": {
          "N60ITzF4Kc9hO6KkDCGLfUeEkZe+AdrkkYAnk44fb+0=": {
            "valueMac": {
              "type": "Buffer",
              "data": "jikOgY2Rek4QNM3iVPTe0Y7fOcfzOmsG6+/x8JCcXVU="
            }
          },
          "EObpY2PELB3gdwp+GhOIXYgbMd+M3E6B6OsuzUYxwRo=": {
            "valueMac": {
              "type": "Buffer",
              "data": "sJL8OATDz+48416/iwGAktn2OPi8urLRy+uf51vGjqA="
            }
          }
        }
      },
      "regular": {
        "version": 1,
        "hash": {
          "type": "Buffer",
          "data": "iCFCbn9Fka7splRFsihqHIzQJvwDvsN7005TgrLekTMu7NWyRys7EpwLzDQ5VLxvxZG33xwzjkph3B0qBVD2mxnaJ6o3XY6FnWlBEnD+/Not5rxdc+uocUI5XGB6eOALvLT1tPvzSLp9OrYbHfGFJKSMnWQhNGD3zYtQqbjBBTY="
        },
        "indexValueMap": {
          "Sw9cWvBGdOUdjM7OGupzRksQWPySqELrkLqVXtwNkgY=": {
            "valueMac": {
              "type": "Buffer",
              "data": "cpkHBs/KRJ9Gu3S6sLWTi87OasWGe6WIcHSxGk1f35Y="
            }
          }
        }
      },
      "critical_unblock_low": {
        "version": 1,
        "hash": {
          "type": "Buffer",
          "data": "HcWwtq4yo7qcafZ9xqsC2T9HrkHlAauhroJhz5Np9q6Il3yKMPqvdyiYz7F32y7h3LCnTPnsRs+mDM8g+Bh2fKdczwDwRDNpbfegQAhR7fPL1YdnLalSghuXPGQpre7TqPMAvARbVmUekueeJUQOtl6txgWU31J/ClIK9PzmaeA="
        },
        "indexValueMap": {
          "Kt5uYYG4EmKdjrufBBk+9mAvEKvnzdqMrUPv7jgpRQM=": {
            "valueMac": {
              "type": "Buffer",
              "data": "3QSa4TVkXIOYpkssmDiGMbdd+GHZSytGd+hN+9I9KrA="
            }
          },
          "5b3k6vycXRuCyM+i/ENjxMLyEru7xuvKK3CWxPm/WcA=": {
            "valueMac": {
              "type": "Buffer",
              "data": "t9hNKcKj4imM6R8OrEfu+zGbhWpVVWTdSIGLAx9PSy4="
            }
          },
          "TAVAs913feXRqmMT45MGgE0hwgt4c3K3fI/GYKlRFYo=": {
            "valueMac": {
              "type": "Buffer",
              "data": "1MKJqrAqnA/VQaoEIOCchTAoh+p0rnY/qL+YZJVmJSs="
            }
          },
          "YN/2VNMDAxfuMULC1J2t6YsAuGS/JfHVk1nCBjBn53g=": {
            "valueMac": {
              "type": "Buffer",
              "data": "kS7TCSpL9VCM3xFv9F0aJEpoAKJRITO1H1SuLjXYwqI="
            }
          },
          "J0tp5U/PvHv4jcUDAxHDmNPoJdBhKfrLZxHW+APhEGs=": {
            "valueMac": {
              "type": "Buffer",
              "data": "U6HlGcgqyVRH1wSpg2Xqz8L7ZDJUfdKoXSNmTvsw7Fw="
            }
          },
          "LCcEvjDd8HuFNGb5SQGRTEZQN8XNh1nG6MtWEqGDVkc=": {
            "valueMac": {
              "type": "Buffer",
              "data": "Ft1MHg7tH3tKZCxXskm1iXrKYxIYvn4itpYpsXVDFRE="
            }
          },
          "DaUOgXX1dZBMqsICdYpSpVjyR8MFBHdgQvw1BHERZ8Q=": {
            "valueMac": {
              "type": "Buffer",
              "data": "2W9+Zlqy0zeM9QB1ArVth52OWHVmnBcRVLUd6aXUm3k="
            }
          },
          "HK8n5nL03w06+gvz6hBHs+yycuiLB8p8pqxZxi54zfs=": {
            "valueMac": {
              "type": "Buffer",
              "data": "ZKw2Ex1U7ShfUexCLDo7xk++EQ7dks9m7vcvhilEA04="
            }
          },
          "TJAFq9nkldgaxTdN1gV0JZIN0tfDxVR7xa2TGKKCwHY=": {
            "valueMac": {
              "type": "Buffer",
              "data": "YdJxVKuwJD9Bj14k07SsX39x1BGIo5uN3Dpdjh5CTmo="
            }
          },
          "il84xytUWdXp1qK69P2rbEE1lwNqVh43PVAY0pNho5E=": {
            "valueMac": {
              "type": "Buffer",
              "data": "ivxIMenVEq11tDWfUVWzVYkKhPBXYW27ledOKsjoL3c="
            }
          },
          "Wz6mNQT4x+b4uFZIVBhQ0RsCCCjmPg8FZXHYUJjboUs=": {
            "valueMac": {
              "type": "Buffer",
              "data": "CyJlZuezq7dhEGJ17ou6veh6OEJeCUpq3DqEOfUc5C0="
            }
          },
          "pcJVwUTvUMWashdI3/Q/fHNK/9mMIRVLGMvUYL/5p8g=": {
            "valueMac": {
              "type": "Buffer",
              "data": "sBsTnw+C1LvMPzwu1kfD8O+326l7NZ4mnWGJNCxmD+0="
            }
          },
          "QfPQ+CBwop8uH87TmDQUwFI7oLV0N3PS0V1FjYhsQh0=": {
            "valueMac": {
              "type": "Buffer",
              "data": "fygMVLPFPT5fMhLqwGpK7iy40rlIQ1TL5dU0Uf8j2j8="
            }
          },
          "vfxAYNeBIeD4AV0+4RcxkrlTyRKcrmsXRQDNvG6Wsk4=": {
            "valueMac": {
              "type": "Buffer",
              "data": "4le6HHCzzlopFv6wgYXMNkX9SzzfwT4PigmVQOZDcME="
            }
          },
          "YMsI9rI6Fv7Pml7/fIeO/C0+FRTZFlROD2dmKINVEpI=": {
            "valueMac": {
              "type": "Buffer",
              "data": "0nETriseqjuDbfSExBK333Tvz/Dia8Dh5NoJmy/OrNY="
            }
          },
          "W4UqxyyRjagHgH9QSe7SrB72St8AxDYfws5Q/JdhifM=": {
            "valueMac": {
              "type": "Buffer",
              "data": "yd8grAIT8gJkkGHSd9daCHfBuC7hoUlKBB3j7/0UFS4="
            }
          },
          "yqVoK28qkK8bEe5ufuU+6dV3UXkVRbDfiho1RlZpMus=": {
            "valueMac": {
              "type": "Buffer",
              "data": "fwKsnWZ7IUzcDwUX7cMvlzzUFvzzACvmj/GMeN1GX1U="
            }
          },
          "t4dq+UEpyIjMC/h60AnVMcKJVuMRDCXNvKxx6BSk1lw=": {
            "valueMac": {
              "type": "Buffer",
              "data": "5EMMnDw58JubwnmuMTjjdR1KmCRXzzsT5nMTn0YP28Y="
            }
          },
          "UIM6buvGlzs+mLwPocapejDVDg5mdLm999AiVoh2Zxk=": {
            "valueMac": {
              "type": "Buffer",
              "data": "u5Oul8k+BeKm647kSB7Fczea+wevwAeDGzm4EkMU708="
            }
          },
          "3GsQ1Zlc4+DtML72hHEh2q1MC3+l1p4OyBdNlKijmh4=": {
            "valueMac": {
              "type": "Buffer",
              "data": "Kd5LwnI3Q7TTHEVKovoDx4EJC2jBoKrn/mIQOIkWbyQ="
            }
          },
          "ji7ej3wiqr+D4KIjMG9hLqd3Mf5JmrPFIlUsG3fhaw0=": {
            "valueMac": {
              "type": "Buffer",
              "data": "by42o+kXz28gdsG/OTvUPlWlzrckHoSHDGmopza8PXc="
            }
          },
          "IscQ0WlOiMdLZsQ6CGWJdgpHHT4ynuocyFO/UzfwTFg=": {
            "valueMac": {
              "type": "Buffer",
              "data": "HBNQrEpbtTKNxUGopealTxmRxG6nb2XqvRW8g5c30QQ="
            }
          },
          "lJe6klIQyr7iVSYONzl/y0g93T+HhLH9pAkACWcLRmM=": {
            "valueMac": {
              "type": "Buffer",
              "data": "bqhwCmpKxhiRK7OCmhyyLmBcwFU1XqcpixEvwbT8gTo="
            }
          },
          "qTnWaMpMaRblCmZZUKEFBhFLYeOhY0uk2OqOdSaNy3M=": {
            "valueMac": {
              "type": "Buffer",
              "data": "x0AGA5JbQGYMrzPE0EHKQfP6XpF8+THLwEqhUx0EreU="
            }
          },
          "7knOxx39Ek3kOnm5N77GDUkb7hF5PVk0Fs0+e3BlMQQ=": {
            "valueMac": {
              "type": "Buffer",
              "data": "QqxojW1K1pVSJKU96kXK2dYv0kQOvSn2jEl8KUn6Alw="
            }
          },
          "GUdlqly40q+/rKgx5mr+ZglL/SMgn4HZg8YqIUuB5Hk=": {
            "valueMac": {
              "type": "Buffer",
              "data": "ypCydwJ+aegzS8UcxY++NIfKv+EIq7EIqKCkSQ8HZvM="
            }
          },
          "rkyYaa6UbI63l1HTtCjZ182AVb35ytLYjmhpfh6BGHs=": {
            "valueMac": {
              "type": "Buffer",
              "data": "KCnUexnLFelpvBa+pAtn4vH/BowUwHnbviZ5OoTDbLI="
            }
          },
          "i7Wq7llebntoHyqSWVfNCaBVfs4bg+qLu+f4mRAVTas=": {
            "valueMac": {
              "type": "Buffer",
              "data": "iV8HWQyhghnAdOdP5uUvP6A5oT9o69glmpj3aFccykM="
            }
          },
          "ovv3H8wIl4h9HYlwGnFMQClmSas6GWXCe/0lMAl8r5g=": {
            "valueMac": {
              "type": "Buffer",
              "data": "7i3Qf4Wg4F3DqUP7xqHAxYHz2qMx7q43D9yYhm+/TP4="
            }
          },
          "cv6GhJ2itVgw+tKv/f7Y5Le6deYPW0GK+iM5mrnSfQg=": {
            "valueMac": {
              "type": "Buffer",
              "data": "m7dPZEvIK9ptByVLi0Q8pFdjI6PtSgrU3UV3RqbV9yY="
            }
          },
          "OF2vU2Ux+ouomCXzvwz14fLn1sJn6oSBhxzQ6357DEA=": {
            "valueMac": {
              "type": "Buffer",
              "data": "ht18YEJ0i/jSmKr1izO/PRpRAwKY9/FqCYAAzWp/t5A="
            }
          },
          "C4x+5l5IMHG7WcjNTXDeA/rurZMLnfFJ500KXCObqa8=": {
            "valueMac": {
              "type": "Buffer",
              "data": "xTP7IOw/RNlmuKeZvCxdLrzgFXiNazgret7Iynppod8="
            }
          },
          "y47slENscdMYS+d07rXJoUGKWMKeRjyfuJDhmeGzSq0=": {
            "valueMac": {
              "type": "Buffer",
              "data": "/xsq6bBi2SXm0Q6LFfDgDs4tzMg3LhiCJUMd3pM0kNo="
            }
          },
          "Cb9m8YItxmBxyfC+X/VylKlsFNI1uvSVaGvH978voBQ=": {
            "valueMac": {
              "type": "Buffer",
              "data": "XtM+vzpaT+/Sn2Qb47y0P2tIYdWaXS/eVUXLUS4xpuU="
            }
          },
          "dfYLwPoZ/qa04tRQRp6cxlB1BenjpqQKvGl7BhgyT0M=": {
            "valueMac": {
              "type": "Buffer",
              "data": "mEUNHaZISxeuAImB3BgjSNnUwQGYIxUhvLp4IE2GBMY="
            }
          },
          "pMcbYgXQ7gpxHYbrZ2/dph2+yTVnSUb0n+ve53QoEvE=": {
            "valueMac": {
              "type": "Buffer",
              "data": "GYuuN10VaTCjcKCh8FPsyuWnEmWtWiyf+lkcIkJCkow="
            }
          },
          "gOZ/qf1tmlKt+IGXNaD9NPNOPOqjmjjafY9JJQgcmfo=": {
            "valueMac": {
              "type": "Buffer",
              "data": "fme9gyQWrlW70lwvcgc5+KdmB4CTU5BJNFVbmhkU6wQ="
            }
          },
          "24HDNeZGIds2RgWvlroyydYBIszPdRx+8cVUHwa3dqQ=": {
            "valueMac": {
              "type": "Buffer",
              "data": "Jw2jGDreydWu1gy9Jtt+9hxb1NCc7JhxbN+twJRnWTg="
            }
          },
          "6774QibEE3DIkbtKm+fsgrKWJS0G9xAdpayCZQukbLw=": {
            "valueMac": {
              "type": "Buffer",
              "data": "p/2c1mSJu7mO5O5dKjfZCK++BXGVcYSh5+ToKu2mcMs="
            }
          },
          "Y6ytbmC6vhA5eSYb3dfWF0hWSAlsbNKImkoX+N+yPMg=": {
            "valueMac": {
              "type": "Buffer",
              "data": "2pRb4tnGsr2QjB733a/lqz04ZAfk9snjO8FsRNvT3dc="
            }
          },
          "sR0uXk7yafUoFqp9Y6ea2WZOmL2oVFbkiZ/GADTKmfc=": {
            "valueMac": {
              "type": "Buffer",
              "data": "sIPJb9id78plgB36bflNXNrjtBRJshRBQTHk9EWY2/0="
            }
          },
          "X3vRcfFy3sr+glUepq4XPNmW8r8zfTKee5yPuSQxHDk=": {
            "valueMac": {
              "type": "Buffer",
              "data": "Gi4l9fl/pydB7lRKFP9s9zj0ai7aq1HZJTuOSDRS8yY="
            }
          },
          "VBDEAXE9qhLZ+WtCSCqqzKMWrGmoZf5nrgw++aG7Iko=": {
            "valueMac": {
              "type": "Buffer",
              "data": "cys59s2+CvMViHwHwXvSjSxIqWQ2dOQEGfYDgYnJtA8="
            }
          },
          "zH6I1e0+SdMVp1Fl9jMp4W/IbWqlYPzgJj//dYW5o4k=": {
            "valueMac": {
              "type": "Buffer",
              "data": "sJgzYNs6pUfzTt4bScHRz1eu5TsezoB9HKBrUmbovII="
            }
          },
          "NMbkJJB2KWAUPoWf9jsCr7zFoxT3RTQIkyKmDcpM1ew=": {
            "valueMac": {
              "type": "Buffer",
              "data": "KEhm6caRMQWIEy8RrhSVd1CApWJD5HwrRFBT+H7/t4Q="
            }
          },
          "/kXDM+G/4dz/fGof85CMZx1zVaeTji/Ip69h2xQMFoQ=": {
            "valueMac": {
              "type": "Buffer",
              "data": "ZYDeSUGSCnjIaAQnZb99E923PTBsW0W9uOt1drF+8bE="
            }
          },
          "51euDkJZqob7xzzFO7KFq0hBkYCgZwYVQU1npNNQUkY=": {
            "valueMac": {
              "type": "Buffer",
              "data": "XntV+2wglH7x0WqCEAQsgtwawNj+rOkZqXybm74tWxU="
            }
          },
          "wau6M0A3I4uQvlsV4cPS42JbQWSg8hu31MH2Js+sIJo=": {
            "valueMac": {
              "type": "Buffer",
              "data": "0V4KPTvmwXgZatxx+ckX4TrRVd+bfM6r657QX3Ptibw="
            }
          },
          "Oqw+8wP7s3mqV9uKFXmv6SfOYlYmOGij+PSJD+MH414=": {
            "valueMac": {
              "type": "Buffer",
              "data": "PAmROTTZ9Rn0cZkcCdl5qEruUip1bFcVRK4AfCH+qDQ="
            }
          },
          "oC1TxMbAI10c481ficx9iqv1gPMyjzDkbWezWRINf3Q=": {
            "valueMac": {
              "type": "Buffer",
              "data": "xN1cvBuC/0UTZ81MuRt6OJNYqxfgQxDFOkNot92Z/HE="
            }
          },
          "bcJFi84r/WP6dTFKyOzaUnwWUZLdDIsEmz4f0w9qHsA=": {
            "valueMac": {
              "type": "Buffer",
              "data": "4rWdteeW3jF5/E/NKoqtJFgVWwHJhZYtmeZRXOaBtQg="
            }
          },
          "+oC/aZHrgKvpCDdRxux4t5ZOtMvIk1izGu9pgKEju48=": {
            "valueMac": {
              "type": "Buffer",
              "data": "FAz4aIhuL8BU5EtQr22mMTWVOR+fV30m3mgABYvIBGE="
            }
          },
          "8xyYJJYRrd7o5ayBwz5r/Co8w3VTQLsPYQr7cTVqMHg=": {
            "valueMac": {
              "type": "Buffer",
              "data": "kECRf+jREaSktL2RPYexOHA58v0ReV/KXeYeKhhZbYI="
            }
          },
          "tgQR3XIL3gXt8KvyEIz0yWWM8fekrPZy66hA40V44IY=": {
            "valueMac": {
              "type": "Buffer",
              "data": "tkVxEw1x35oI0oPM83gbnmRGYGjwtbQXqR7/HWqcu+I="
            }
          },
          "8cUjNb1T49g7OXZc2S9f0S/IgQT8IAeUyWUXJmnAvoY=": {
            "valueMac": {
              "type": "Buffer",
              "data": "BAaWwwBFb6Ixd5Y+x46ajb+DYg2R6n54hibS8Ik7xk4="
            }
          },
          "VuDlj+4l3VRUyr1/HIMbGAoMdxHVWnFTXUJ34Wb476s=": {
            "valueMac": {
              "type": "Buffer",
              "data": "L5nAv10q/7zNpX1gxZL8qcnpRd72EzdRPb6SGRg+94A="
            }
          },
          "bvki2kx6xgdRcvIJrLn6RT81rgVQ88hj8CTf7XWaURE=": {
            "valueMac": {
              "type": "Buffer",
              "data": "zPUM74DTS9qoYDXbTy7OR5bYKF71tCbH6uxFKyaZF8w="
            }
          },
          "NbQYcoARohD8m5ZpLtDhfgsxUtENTRGuCuJ8+R/jo6A=": {
            "valueMac": {
              "type": "Buffer",
              "data": "D/MWgj4uIUzcR6Wb0Z2ocHJfCHvR4QU2rheAbHVpX9A="
            }
          },
          "K5vnJdWVCeUHwMSYTHzasqwW7SXywRwjHNy8sIwvPZo=": {
            "valueMac": {
              "type": "Buffer",
              "data": "24VK+2IfDW8Ps05OucB0kI28fMrInFDAWa6mbNIcPvc="
            }
          },
          "flmAz1Sl+y+PqW2aRcir8eZ3cDjJLAA3kLncg10Qe/s=": {
            "valueMac": {
              "type": "Buffer",
              "data": "oq4bkn1q3grIPIzC5QBK2CSSv6/ildpYe0kSzL5AiEA="
            }
          },
          "Jik0Wfl3dE53o6rRIg4JO+kaPb/HZtOErZ7DlDlwIKM=": {
            "valueMac": {
              "type": "Buffer",
              "data": "PF9oLKLuzeHnXocsxH5QFahZ7Zufl35eYVu4dSZlUqk="
            }
          },
          "lOqFJ2Ra0jzoEC54tzD/tDny7HKwCfe2ENnW+Yr5CAI=": {
            "valueMac": {
              "type": "Buffer",
              "data": "XbmO4TJIpH4gYUKwCMLMtUigMcp3a8C1YmfC2p7WMy4="
            }
          },
          "UcY0XpFX8sxjJFT1E2ed7ymvCNzagfFbWjUokNIMUsA=": {
            "valueMac": {
              "type": "Buffer",
              "data": "K8cpc5jLBQU21/6mE8wBFEg/aA98Rp36PS5jmFcnDGo="
            }
          },
          "SQF1pUNkMadHvbH4NMuojxidZTaUW7t94VZ7DWa+O3w=": {
            "valueMac": {
              "type": "Buffer",
              "data": "evEBnNBIEr0zrg1uLUMRdDOxRx66l+DvAFIh+C5MDBI="
            }
          },
          "ctlXnHK2IQK12XDW1kJT/hAspjOhN7P0tRsvQzcsWi4=": {
            "valueMac": {
              "type": "Buffer",
              "data": "aByc4C5SFyfznPqHiP/QHRaB/469W8LQUMeJdoOlyG4="
            }
          },
          "cw0VXVJyXmbyf4GMnXfuvsTBYRbuqJKf23a7idGZifc=": {
            "valueMac": {
              "type": "Buffer",
              "data": "wOZZDocrDpJJ6fNQhplEOIEVmGGXLjf+QjZ5miwfLyA="
            }
          },
          "VrMkf+V81z9PByxw6QqZjrOtT1eiOnlL43yOszIZZPA=": {
            "valueMac": {
              "type": "Buffer",
              "data": "IPTBz9Xe+i2cedl8Sas+FLJ0h1LugKJbsIwQGgkum0w="
            }
          },
          "siJnppYHjBDS4vJWgOVJCyNaujSCkyuqX52sDJhp/vw=": {
            "valueMac": {
              "type": "Buffer",
              "data": "mabyxFaPZba3C+aBo+ZRswNAy7VCO4R8Mda4qZ3gBhw="
            }
          },
          "tQ4en0NZ/M6HfYNKL5DSDaBVI8sg0DObVRYB3UTz1V8=": {
            "valueMac": {
              "type": "Buffer",
              "data": "UG5vmVnAxQjT2Lb3A5QgOs+JfisvdGpHDPVD/Qn3Kyw="
            }
          },
          "U0bvR1pqn6k+6tS4ZcdTcr3M16JljrmDHqYMnaNvSA0=": {
            "valueMac": {
              "type": "Buffer",
              "data": "tKZ43/1I2M1LqeSHC6ETD6hZqaAIobr7Z3HU37oNgw8="
            }
          },
          "gDllA36rrpHdAi0vzvl3V/s3J2DU2mFveLo+WsDiGZY=": {
            "valueMac": {
              "type": "Buffer",
              "data": "/yCDVbBLvlrFmCi19f+5PPJe3BayAY9q7vpRjxmgTzA="
            }
          },
          "/Kul2zSZFGy1NnG+VN+2sD7SQ08mCjSx1BMea0h6EDc=": {
            "valueMac": {
              "type": "Buffer",
              "data": "7Sw92QDQQtmF88itVw0gO2ZBAMf4oJVQ9aLbdIOC384="
            }
          },
          "Hzi90PUq/CZK/Qz5aYu/Z54oNBX0Z72GAJYd2SRC6W4=": {
            "valueMac": {
              "type": "Buffer",
              "data": "Zc5+fuUcbLxXTD5OHGQ/Z2dFmphNg2/fefzZuLWX2Ak="
            }
          },
          "5FfOdS1M8QnnD7lGLn7AjT1BWCaISrcwIx0S4tZ1ea4=": {
            "valueMac": {
              "type": "Buffer",
              "data": "Hbeipj4TpcTnWc7/o/w0W9fdD7U0cBJ5ga7PHYd7rlg="
            }
          },
          "KZPpjEgXAl2HdJDXtiLS5GqM41RbROmQxpZxA4b50uE=": {
            "valueMac": {
              "type": "Buffer",
              "data": "+79827FiVAXwSKgRdN1Tv+XT0gXohNJ7QD5vrzXT1Dw="
            }
          },
          "og40Q4e2qP1iZ4tVCX/qOYpoqibpEycZpgMecAtLbsc=": {
            "valueMac": {
              "type": "Buffer",
              "data": "jF6tOtrCqLJ0gTsiOPxpfYosY+Z6sxXQHOOLec6DqRU="
            }
          },
          "hdY8oNhgA6xa7Czrju66AnEBZUILBcIlnLYEToKHgUk=": {
            "valueMac": {
              "type": "Buffer",
              "data": "JkYIufMVjTbADinccVoU3ljo5nyerpra4/dYqCfILTk="
            }
          },
          "8O5kQUFYlznUADwBP7f5PcolfMIGPYUJCgu9wXxv/KU=": {
            "valueMac": {
              "type": "Buffer",
              "data": "v0UueSKobF/bM2GCkUJiuhv7vRb4/cqMTYHHJTtt9eA="
            }
          },
          "ZRWOUO1UeLdSe0BjLI3iFrbGp8oZRbFDgEh18fKzMkY=": {
            "valueMac": {
              "type": "Buffer",
              "data": "RGnnGvFS4Y1V5uk7o5nDPUHHm2SUdXj5p1GKJL9Irfk="
            }
          },
          "YLdsibQsbiCN7BvwwDEhFpqKwBd/Rn++6wSPsvbTxs0=": {
            "valueMac": {
              "type": "Buffer",
              "data": "Cyttuw1Hwt99B2410CGitYYz/FBbGN5wxhjg3Sy7fMc="
            }
          },
          "EmZSLBrvRRzBedBTpveHzT8dMRJrtz3CqL7OIgcVoI8=": {
            "valueMac": {
              "type": "Buffer",
              "data": "Y1/s3D+EdQSEOrnaYs6tb3dB+Nc/NrXCCcrr98Mh9nU="
            }
          },
          "kHemMmlpRyPRR8uT1jMGW+eavgODKFUsqqrSLZww5yg=": {
            "valueMac": {
              "type": "Buffer",
              "data": "gc5YQtR2XACCaYEMdE41g53ssQwKgsbeuCTvb8Tb26I="
            }
          },
          "qWID/hBwyt+pyNUW1Rc9C/ZKYhtho/t3kScT9GA1XZ4=": {
            "valueMac": {
              "type": "Buffer",
              "data": "shxbeIUuo+PbN0ytpMhPrSxSwnEoTCxrLhK83CNrbQQ="
            }
          },
          "fabCdGuVFzzSm7LQaTTtdLdrdQk2IvP/xKwFDFIh0SY=": {
            "valueMac": {
              "type": "Buffer",
              "data": "XiwyNYH4SdoAyzoh+JdrTi58sOh4BNB840enmK7uG74="
            }
          },
          "ZeCw/EDoGOTiubMcNySNoH3L6c2O059PGCdennJZyW8=": {
            "valueMac": {
              "type": "Buffer",
              "data": "YDMICU1lKezfT3xRb8rDQ7cOs/03COCruKqp6YNN5+E="
            }
          },
          "F1KcWGpYuPMHM8zAREYckVoj7NF4YmKN+OlHkYZISvY=": {
            "valueMac": {
              "type": "Buffer",
              "data": "TzeU0APQRVjAt9ISe9BihYbOJlSM5ltlmcTPb6yEIY8="
            }
          },
          "7fPSKo2o4IWA9C2uyXa0L5qVhZrwg+zx6QrBAyGfxW4=": {
            "valueMac": {
              "type": "Buffer",
              "data": "GS4q+PZrVoYXWHOo8xzgKBxoWcIehYmLVxJ2pxLwJsM="
            }
          },
          "vT68k8TkSxjFKY9qf/n5QxVhM9RR8xcvB9O5i5ij7l0=": {
            "valueMac": {
              "type": "Buffer",
              "data": "Miz+43wXrgUq5hx72z6Q6oIP4cjCxrlBa1KaJOn8XDY="
            }
          },
          "V3XdaQ6eF00/X2sslcF05ElJhfYBwc+Da+dldQNWHOY=": {
            "valueMac": {
              "type": "Buffer",
              "data": "9sayQkSkiwMBZGeJsl3uokdzEaGSQMjsFwFbouPi4j8="
            }
          },
          "qptocM2hUWZU8Ec1v1LtelRR7lQ7R0ezqOAPLtChF90=": {
            "valueMac": {
              "type": "Buffer",
              "data": "pcxYZkNXMmcsOPq8PzhIU4clKkmLTjO3BoWw+1VLRNA="
            }
          },
          "XTromDduns+cAdz57R84JUAyuRMZ1mXX2x9pTKaWTYg=": {
            "valueMac": {
              "type": "Buffer",
              "data": "415LgTMJbmZVJwBfolRe9a6F2EpYP2Wgoy3AN+0zVGA="
            }
          },
          "fDPGiK0HXTmoi6lokhCbcm5aNEINrXfQ8Cx/NWDFAjo=": {
            "valueMac": {
              "type": "Buffer",
              "data": "6DMwzpYtStjflowFFhWlCLRpyLqnYDepEJpfwUHJOhE="
            }
          },
          "AO4ml7sKnaN5U5ljYe0TIMvPr81nIG7c1J3/6UxjGvg=": {
            "valueMac": {
              "type": "Buffer",
              "data": "eyiLtuHyPpv6GR6b4X72AQgdfGAwTyYoWdDvHHw8XmA="
            }
          },
          "9HkSn9BJNfaNaw2byAq3KC97zBaIQz3AZ9jIGZhHsxo=": {
            "valueMac": {
              "type": "Buffer",
              "data": "sIYZJgaLlyAw3TFGxvcAdTPN/xH8nny3TcY5gCMNJr8="
            }
          },
          "Ow6q9cweaav2q0WmV8qOsM/l095CJkxOg53ayCh99do=": {
            "valueMac": {
              "type": "Buffer",
              "data": "Fb32y64sqVS3ELK5uPMPJg7VQi3Ubs3nXkYImP9AhMQ="
            }
          },
          "H1FmLGAcGuvJL0NyvASeTrxyCK8xVLSM3Hiq6ASbKp4=": {
            "valueMac": {
              "type": "Buffer",
              "data": "EibjadZOPy0lcrRwdj15xD8PYTLUyumb0kp4nb6AZH4="
            }
          },
          "y4Ra5btusr7D44xww09zPLqeDYJWJxpmq1PE/jt50Mw=": {
            "valueMac": {
              "type": "Buffer",
              "data": "AMH4DDNIFCOVgCh+/65h6YzkgAH0/FzT/hbW/51+ZdE="
            }
          },
          "5qejzMd51WZ2imjs3IfK82j1fGzES8f262qEDdPNaXU=": {
            "valueMac": {
              "type": "Buffer",
              "data": "hgY/cINOZag7EFgE6r+StrVmKtjg08RspcRe2GeOVeg="
            }
          },
          "8gT6eZeRMPW9B4O7hAPg8BRSRjZQtwvDLTTPLOhylDY=": {
            "valueMac": {
              "type": "Buffer",
              "data": "dP5Rm9wADduQ20VSFOxn2GqUMPL1B2P0NBFIRoGYRAw="
            }
          },
          "zjO0c70hOxFhI401SaNNXrlR32spGG3FChUgLAcGgho=": {
            "valueMac": {
              "type": "Buffer",
              "data": "973HcHcjeFG67bSXNv4hBNCeRAzTpBYdd7g6TTMfUrg="
            }
          },
          "omL0IlO7/lOmhIoTzJJIEgP8JIYB2wzt2tkUxhdSlD8=": {
            "valueMac": {
              "type": "Buffer",
              "data": "6VYDX7vIVTwobIPlv9RmEUct7zS1do5nTQ3NpchUpUo="
            }
          },
          "NuUOQPgFVegc8kXw2NiT896VKa+mUm8DO3Y3JdmMCbM=": {
            "valueMac": {
              "type": "Buffer",
              "data": "ePe/jZiFg56ySFV5/xzEjvqsNAzk4D27xwxfj+faWyw="
            }
          },
          "/Zsy4CpJMfQroY0ncgqRrv/JkMRoXJUg9domdH+7LE4=": {
            "valueMac": {
              "type": "Buffer",
              "data": "D8sKJkOp6cqqER0UKgobm7/MWgL/8z0um6h1Mx9x9Xc="
            }
          },
          "bt1VLfYtZQ1jYTAAnvh7iOjcx9OIKYrPWx0O+62dlHM=": {
            "valueMac": {
              "type": "Buffer",
              "data": "qWoBuhLEnbP9ZF2g7ZwMgwXlzVKfBKisghChNlVADLA="
            }
          },
          "F7dw4ueRoYnEVr5nBWVbE756YAs1dVJq2kvwsKYOQXU=": {
            "valueMac": {
              "type": "Buffer",
              "data": "ArCpI/iVfgx5AKG5EUv2SOFf6d0ayjwB6vyKmevi1JQ="
            }
          },
          "+zJqAw/PBMrXuZ0k+zV5ueEkBgdCSpXf5lkvcIKQpEc=": {
            "valueMac": {
              "type": "Buffer",
              "data": "EAq+Fdgg9lPU7jp2C+MjkMjs07hG39f3aeA5G9sjE3o="
            }
          },
          "yG3jBAfev971DJBpb6sdMGb2rL6Km1E7j4j9MGN0Zh4=": {
            "valueMac": {
              "type": "Buffer",
              "data": "P555bXztLvzWF5vgZxUK8TxaVHLSvWgsDVTjOq9jJOE="
            }
          },
          "rTxGtCsCYPxC3nSVi8Qd2X/VMlyFtfF00DfEpHif1wU=": {
            "valueMac": {
              "type": "Buffer",
              "data": "vmy1RHGs2jThvI6GKFpul0pzyC9r4DRFPv/Twf/uR1c="
            }
          },
          "GVjzUv3cezGR4Y98oF3ToqpnDInlCURqLwLYlGPUAwk=": {
            "valueMac": {
              "type": "Buffer",
              "data": "WzihiXOUk3KVhPqzh+odmW3vmPNTZkGMT8b1aihHgx4="
            }
          },
          "+iaOu93DaU6E0tY8QOHlWAYCr9gm94wBJ/etF32baGo=": {
            "valueMac": {
              "type": "Buffer",
              "data": "5ZgWrn7L5qX7nuPKnp1g9ETH6wo8lzKJ8pImrs0NSW4="
            }
          },
          "uZT0xiVYdCO/jwcEs7DZrLB6nbgt+r5LaVpKFAPsjwM=": {
            "valueMac": {
              "type": "Buffer",
              "data": "9q/piASjGm7vrv0TmNGgJQV1B4o8fFucMgxDcJMg+0A="
            }
          },
          "ZOfsPgzOoF2JOIMHIPEQEiSyF6UwyfD5mpBh6OgTYfU=": {
            "valueMac": {
              "type": "Buffer",
              "data": "t5RTxvNIG/W7qbT6GHfye9HQTgv2r1SFCavkw3HalNM="
            }
          },
          "V6+KmnJpoZ/yVUGAaLEO7pgHCdbhIbai9QuNCnBFFAI=": {
            "valueMac": {
              "type": "Buffer",
              "data": "4MwBbFaSWBhPGQIAOIwv536AfnXOCQ/daap5jvKwAxc="
            }
          },
          "ozzC4Z6W+Bkiz2l/KMrnuLVGmL65Ms89mn9JIg9T45Y=": {
            "valueMac": {
              "type": "Buffer",
              "data": "ubyyjV2znSLn48MNWhRk4aAEoRyB1N0DQs6g8z85Q34="
            }
          },
          "kuycKzLO0Z3Y0aLT62VWK499VF3T+qd5a2Q1mq/GT/s=": {
            "valueMac": {
              "type": "Buffer",
              "data": "mr+DIyuwfj7zOQwLJT9OlYimTRtK6POi62ujcmEv5Rw="
            }
          }
        }
      },
      "regular_low": {
        "version": 1,
        "hash": {
          "type": "Buffer",
          "data": "pPHL8qEKbmZIJxMnH5FiXkuNbdxf6Dioa952aVfMEoqpwkf4jO5tbJxnjf1MyashO7K9gdLFeMP7PrjiarfyfITTeA0G15/X2uYJPvGyWitDmYF7nEwtB+CNmg76cTNrTyu7rrP4IzG6XFEuwrdBo6MW5kaDGAq7J5U9daAe35A="
        },
        "indexValueMap": {
          "Xjg/uU5yI7PFlNPo0FzEY2MsJsb4YGumt7TrWiOgeac=": {
            "valueMac": {
              "type": "Buffer",
              "data": "PwI083NP2lGWw6kM1MF7gs8LGztgzGwfWSo6513i7hE="
            }
          },
          "qEEwDt3QHrN/SboFCR5WQeG5UdXwAOZIfTsRP+4utQ0=": {
            "valueMac": {
              "type": "Buffer",
              "data": "U4FINftXaHCuezwvhPwtuHBfBuq57F5Yc+MZ3c4NuoA="
            }
          }
        }
      }
    },
    "senderKeys": {
      "status@broadcast::50946058112::0": [
        {
          "senderKeyId": 942387043,
          "senderChainKey": {
            "iteration": 0,
            "seed": "QoW63Fzla+9GeMU4ID6jSOPUicn3tyKB1jsKionCQrA="
          },
          "senderSigningKey": {
            "public": "BSsjvhZ28j50wfy/XloL+fFSzomD0D1/JxUbDtiTwh4a"
          }
        }
      ]
    }
  }
}